{
  "public": {
    "port": 8080,
    "name": "public_api",
    "tls": {
      "cert": "./certs/cert.pem",
      "key": "./certs/key.pem"
    }
  },
  "logger": {
    "level": "debug",
    "encoding": "console"
  },
  "mqttStore": {
    "host": "103.165.142.44",
    "port": 9093,
    "enabled": true,
    "name": "mqtt_gateway",
    "username": "",
    "password": "",
    "level": "debug"
  },
  "sqlite": {
    "connection": "./db/emb.db"
  },
  "deviceInfo": {
    "deviceId": "ltd_test_01"
  }
}